hugtokencraft/__init__.py
hugtokencraft/editor.py
hugtokencraft-0.1.0.dist-info/LICENSE
hugtokencraft-0.1.0.dist-info/METADATA
hugtokencraft-0.1.0.dist-info/WHEEL
hugtokencraft-0.1.0.dist-info/top_level.txt
hugtokencraft-0.1.0.dist-info/RECORD
