Metadata-Version: 2.1
Name: hugtokencraft
Version: 0.1.0
Summary: HugTokenCraft is a user-friendly Python library that simplifies the process of modifying the vocabulary of a PreTrainedTokenizer from HuggingFace Transformers, making it accessible without additional training.
Home-page: https://github.com/MDFahimAnjum/HugTokenCraft
Author: Fahim Anjum
Author-email: dr.fahim.anjum@gmail.com
Classifier: Programming Language :: Python :: 3
Classifier: License :: OSI Approved :: MIT License
Classifier: Operating System :: OS Independent
Requires-Python: >=3.9
License-File: LICENSE
